pydoris/__init__.py
pydoris/doris_client.py
pydoris/sqlalchemy/__init__.py
pydoris/sqlalchemy/datatype.py
pydoris/sqlalchemy/dialect.py
pydoris_custom-1.1.0.dist-info/licenses/LICENSE
pydoris_custom-1.1.0.dist-info/METADATA
pydoris_custom-1.1.0.dist-info/WHEEL
pydoris_custom-1.1.0.dist-info/top_level.txt
pydoris_custom-1.1.0.dist-info/RECORD
